cloudmesh.pi-0.0.3-py2.7-nspkg.pth
cloudmesh/pi/__init__.py
cloudmesh/pi/barometer.py
cloudmesh/pi/button.py
cloudmesh/pi/buzzer.py
cloudmesh/pi/grove_rgb_lcd.py
cloudmesh/pi/joystick.py
cloudmesh/pi/led.py
cloudmesh/pi/temperature.py
cloudmesh.pi-0.0.3.dist-info/DESCRIPTION.rst
cloudmesh.pi-0.0.3.dist-info/METADATA
cloudmesh.pi-0.0.3.dist-info/RECORD
cloudmesh.pi-0.0.3.dist-info/WHEEL
cloudmesh.pi-0.0.3.dist-info/metadata.json
cloudmesh.pi-0.0.3.dist-info/namespace_packages.txt
cloudmesh.pi-0.0.3.dist-info/top_level.txt
